dataci/__init__.py
dataci-0.1.dist-info/LICENSE
dataci-0.1.dist-info/METADATA
dataci-0.1.dist-info/WHEEL
dataci-0.1.dist-info/top_level.txt
dataci-0.1.dist-info/RECORD
