Metadata-Version: 2.1
Name: dataci
Version: 0.1
Summary: data oriented unittest framework
Home-page: https://github.com/JackonYang/dataCI
Author: Jackon Yang
Author-email: i@jackon.me
License: MIT
Platform: UNKNOWN
